aka/__init__.py
aka/compile.py
jackjtools/__init__.py
jackjtools/web.pyd
upload/__init__.py
upload/web.pyd
jackjtools-1.0.3.dist-info/METADATA
jackjtools-1.0.3.dist-info/WHEEL
jackjtools-1.0.3.dist-info/top_level.txt
jackjtools-1.0.3.dist-info/RECORD
