Metadata-Version: 2.1
Name: jackjtools
Version: 1.0.3
Summary: jackjtools
Author: tomzmagic
Author-email: pi_sender@163.com
Requires-Dist: requests
